json_templates/__init__.py
jsontemplates-0.1.0.dist-info/LICENSE
jsontemplates-0.1.0.dist-info/METADATA
jsontemplates-0.1.0.dist-info/WHEEL
jsontemplates-0.1.0.dist-info/top_level.txt
jsontemplates-0.1.0.dist-info/RECORD
