Metadata-Version: 2.1
Name: jsontemplates
Version: 0.1.0
Summary: A small python module for populating json template files.
Home-page: https://gitlab.com/Jon.Keatley.Folio/json-templates
Author: Jon Keatley
License: UNKNOWN
Project-URL: Source Code, https://gitlab.com/Jon.Keatley.Folio/json-templates
Platform: UNKNOWN
Classifier: Development Status :: 3 - Alpha
Classifier: Programming Language :: Python :: 3
Classifier: License :: OSI Approved :: MIT License
Classifier: Operating System :: OS Independent
Requires-Python: >=3.5
